constellationdaq-0.6.1.dist-info/METADATA
constellationdaq-0.6.1.dist-info/WHEEL
constellationdaq-0.6.1.dist-info/entry_points.txt
constellation/core/__init__.py
constellation/core/base.py
constellation/core/chirp.py
constellation/core/chirpmanager.py
constellation/core/commandmanager.py
constellation/core/chp.py
constellation/core/cmdp.py
constellation/core/cscp.py
constellation/core/cdtp.py
constellation/core/controller.py
constellation/core/configuration.py
constellation/core/error.py
constellation/core/fsm.py
constellation/core/heartbeatchecker.py
constellation/core/heartbeater.py
constellation/core/logging.py
constellation/core/monitoring.py
constellation/core/multicast.py
constellation/core/network.py
constellation/core/protocol.py
constellation/core/py.typed
constellation/core/receiver_satellite.py
constellation/core/satellite.py
constellation/core/transmitter_satellite.py
constellation/core/message/__init__.py
constellation/core/message/cscp1.py
constellation/core/message/cdtp2.py
constellation/core/message/exceptions.py
constellation/core/message/msgpack_helpers.py
constellation/core/message/multipart.py
constellation/satellites/__init__.py
constellation/satellites/CaenHV/__main__.py
constellation/satellites/CaenHV/CaenHV.py
constellation/satellites/CaenHV/lib_caen_ndt1470.py
constellation/satellites/H5DataWriter/__main__.py
constellation/satellites/H5DataWriter/H5DataWriter.py
constellation/satellites/Influx/__main__.py
constellation/satellites/Influx/Influx.py
constellation/satellites/Keithley/__main__.py
constellation/satellites/Keithley/Keithley.py
constellation/satellites/Keithley/Keithley2410.py
constellation/satellites/Keithley/KeithleyInterface.py
constellation/satellites/LakeShore218/__main__.py
constellation/satellites/LakeShore218/LakeShore218.py
constellation/satellites/LeCroy/__main__.py
constellation/satellites/LeCroy/LeCroySatellite.py
constellation/satellites/Mariner/__main__.py
constellation/satellites/Mariner/Mariner.py
constellation/satellites/PyDevNullReceiver/__main__.py
constellation/satellites/PyDevNullReceiver/PyDevNullReceiver.py
constellationdaq-0.6.1.dist-info/RECORD
