Metadata-Version: 2.1
Name: ConstellationDAQ
Version: 0.6.1
Summary: The Autonomous Control and Data Acquisition System for Dynamic Experimental Setups
Author: Constellation Authors
License: EUPL-1.2
Classifier: Development Status :: 4 - Beta
Classifier: Programming Language :: Python
Classifier: Programming Language :: Python :: 3
Classifier: Programming Language :: Python :: 3.11
Classifier: Programming Language :: Python :: 3.12
Classifier: Programming Language :: Python :: 3.13
Classifier: Programming Language :: C++
Classifier: Operating System :: Unix
Classifier: License :: OSI Approved
Classifier: License :: OSI Approved :: European Union Public Licence 1.2 (EUPL 1.2)
Classifier: Intended Audience :: Science/Research
Classifier: Topic :: Scientific/Engineering
Project-URL: Homepage, https://constellation.pages.desy.de/
Project-URL: Repository, https://gitlab.desy.de/constellation/constellation
Requires-Python: >=3.11
Requires-Dist: pyzmq
Requires-Dist: msgpack
Requires-Dist: python-statemachine>=2.3.3
Requires-Dist: numpy
Requires-Dist: psutil
Requires-Dist: rich
Provides-Extra: dev
Requires-Dist: build; extra == "dev"
Requires-Dist: black; extra == "dev"
Requires-Dist: flake8; extra == "dev"
Requires-Dist: flake8-pyproject; extra == "dev"
Requires-Dist: mypy; extra == "dev"
Requires-Dist: types-psutil; extra == "dev"
Requires-Dist: types-pygments; extra == "dev"
Requires-Dist: isort; extra == "dev"
Provides-Extra: test
Requires-Dist: pytest; extra == "test"
Requires-Dist: pytest-cov; extra == "test"
Requires-Dist: pytest-sugar; extra == "test"
Provides-Extra: docs
Requires-Dist: sphinx; extra == "docs"
Requires-Dist: sphinx-autobuild; extra == "docs"
Requires-Dist: pydata_sphinx_theme; extra == "docs"
Requires-Dist: myst-parser; extra == "docs"
Requires-Dist: ablog; extra == "docs"
Requires-Dist: breathe; extra == "docs"
Requires-Dist: sphinxcontrib-plantuml; extra == "docs"
Requires-Dist: sphinxcontrib-spelling; extra == "docs"
Requires-Dist: sphinx_design; extra == "docs"
Requires-Dist: sphinx-favicon; extra == "docs"
Requires-Dist: sphinx-copybutton; extra == "docs"
Requires-Dist: PyYAML; extra == "docs"
Requires-Dist: python-gitlab; extra == "docs"
Requires-Dist: python-slugify; extra == "docs"
Provides-Extra: cli
Requires-Dist: ipython; extra == "cli"
Requires-Dist: traitlets; extra == "cli"
Requires-Dist: pygments; extra == "cli"
Provides-Extra: caenhv
Requires-Dist: pycaenhv>=0.03; extra == "caenhv"
Requires-Dist: pyserial; extra == "caenhv"
Provides-Extra: hdf5
Requires-Dist: h5py; extra == "hdf5"
Requires-Dist: numpy; extra == "hdf5"
Provides-Extra: influx
Requires-Dist: influxdb-client; extra == "influx"
Provides-Extra: keithley
Requires-Dist: pyserial; extra == "keithley"
Provides-Extra: lecroy
Requires-Dist: lecrunch3>=3.0.3; extra == "lecroy"
Requires-Dist: numpy; extra == "lecroy"
Provides-Extra: visa
Requires-Dist: pyvisa; extra == "visa"
Requires-Dist: pyvisa-py; extra == "visa"
Requires-Dist: pyserial; extra == "visa"
Requires-Dist: zeroconf; extra == "visa"
